{
	"format_version": "1.12.0",
	"minecraft:geometry": [
		{
			"description": {
				"identifier": "geometry.unknown",
				"texture_width": 32,
				"texture_height": 32,
				"visible_bounds_width": 4,
				"visible_bounds_height": 4,
				"visible_bounds_offset": [0, 0, 0]
			},
			"bones": [
				{
					"name": "gun_body2",
					"pivot": [-0.475, -5.025, 1.5]
				},
				{
					"name": "gun_body",
					"parent": "gun_body2",
					"pivot": [-0.475, -5.025, 1.5],
					"cubes": [
						{
							"origin": [-0.499, -7.375, 7.3],
							"size": [1, 3.35, 1.95],
							"pivot": [-0.38385, -7.125, 9],
							"rotation": [22.5, 0, 0],
							"uv": {
								"north": {"uv": [0, 10], "uv_size": [1, 3.5]},
								"east": {"uv": [0, 0], "uv_size": [2, 3.5]},
								"south": {"uv": [1, 10], "uv_size": [1, 3.5]},
								"west": {"uv": [2, 0], "uv_size": [2, 3.5]},
								"up": {"uv": [6, 13], "uv_size": [1, 2]},
								"down": {"uv": [0, 16], "uv_size": [1, -2]}
							}
						},
						{
							"origin": [-0.00385, -7.0875, 4.975],
							"size": [0, 1.45, 2],
							"uv": {
								"north": {"uv": [0, 0], "uv_size": [0, 1.5]},
								"east": {"uv": [4, 10], "uv_size": [2, 1.5]},
								"south": {"uv": [0, 0], "uv_size": [0, 1.5]},
								"west": {"uv": [6, 10], "uv_size": [2, 1.5]},
								"up": {"uv": [0, 0], "uv_size": [0, 2]},
								"down": {"uv": [0, 2], "uv_size": [0, -2]}
							}
						},
						{
							"origin": [-1.04385, -6.125, 4.5],
							"size": [2.1, 1, 0.5],
							"uv": {
								"north": {"uv": [10, 6.5], "uv_size": [2, 1]},
								"east": {"uv": [4, 16.5], "uv_size": [0.5, 1]},
								"south": {"uv": [10, 8.5], "uv_size": [2, 1]},
								"west": {"uv": [16, 4.5], "uv_size": [0.5, 1]},
								"up": {"uv": [15, 7], "uv_size": [2, 0.5]},
								"down": {"uv": [15, 8.5], "uv_size": [2, -0.5]}
							}
						},
						{
							"origin": [-0.59885, -4.89169, 6.79621],
							"size": [1.21, 1.075, 0.8],
							"pivot": [0.10115, -5.54169, 7.47121],
							"rotation": [-45, 0, 0],
							"uv": {
								"north": {"uv": [2, 7], "uv_size": [1, 1]},
								"east": {"uv": [9, 6], "uv_size": [1, 1]},
								"south": {"uv": [9, 15], "uv_size": [1, 1]},
								"west": {"uv": [15, 9], "uv_size": [1, 1]},
								"up": {"uv": [10, 15], "uv_size": [1, 1]},
								"down": {"uv": [15, 11], "uv_size": [1, -1]}
							}
						},
						{
							"origin": [-0.61885, -4.425, 7.6],
							"size": [1.25, 0.95, 1.25],
							"uv": {
								"north": {"uv": [14, 2], "uv_size": [1.5, 1]},
								"east": {"uv": [14, 13], "uv_size": [1.5, 1]},
								"south": {"uv": [14, 14], "uv_size": [1.5, 1]},
								"west": {"uv": [15, 0], "uv_size": [1.5, 1]},
								"up": {"uv": [2, 13], "uv_size": [1.5, 1.5]},
								"down": {"uv": [13, 4.5], "uv_size": [1.5, -1.5]}
							}
						},
						{
							"origin": [-0.75, -5.6251, 3.28506],
							"size": [1.5, 0.5, 3.5],
							"uv": {
								"north": {"uv": [11, 16], "uv_size": [1.5, 0.5]},
								"east": {"uv": [16, 12], "uv_size": [1.5, 0.5]},
								"south": {"uv": [13, 16], "uv_size": [1.5, 0.5]},
								"west": {"uv": [16, 13], "uv_size": [1.5, 0.5]},
								"up": {"uv": [13, 11], "uv_size": [1.5, 1.5]},
								"down": {"uv": [12, 14.5], "uv_size": [1.5, -1.5]}
							}
						},
						{
							"origin": [-0.75, -5.14088, 4.99756],
							"size": [1.5, 0.0125, 2.1],
							"uv": {
								"north": {"uv": [11, 16], "uv_size": [1.5, 0.5]},
								"east": {"uv": [16, 12], "uv_size": [1.5, 0.5]},
								"south": {"uv": [13, 16], "uv_size": [1.5, 0.5]},
								"west": {"uv": [16, 13], "uv_size": [1.5, 0.5]},
								"up": {"uv": [13, 11], "uv_size": [1.5, 1.5]},
								"down": {"uv": [12, 14.5], "uv_size": [1.5, -1.5]}
							}
						},
						{
							"origin": [-0.86131, -4.90282, 5.625],
							"size": [1.75, 2, 2],
							"uv": {
								"north": {"uv": [4, 8], "uv_size": [2, 2]},
								"east": {"uv": [8, 7], "uv_size": [2, 2]},
								"south": {"uv": [9, 0], "uv_size": [2, 2]},
								"west": {"uv": [9, 2], "uv_size": [2, 2]},
								"up": {"uv": [9, 4], "uv_size": [2, 2]},
								"down": {"uv": [8, 11], "uv_size": [2, -2]}
							}
						},
						{
							"origin": [-0.98631, -5.15282, 6.125],
							"size": [2, 2.5, 1],
							"uv": {
								"north": {"uv": [0, 7], "uv_size": [2, 2.5]},
								"east": {"uv": [11, 12], "uv_size": [1, 2.5]},
								"south": {"uv": [7, 0], "uv_size": [2, 2.5]},
								"west": {"uv": [13, 0], "uv_size": [1, 2.5]},
								"up": {"uv": [4, 3], "uv_size": [2, 1]},
								"down": {"uv": [13, 6], "uv_size": [2, -1]}
							}
						},
						{
							"origin": [-0.74385, -2.925, 5.625],
							"size": [1.5, 0.4, 2],
							"uv": {
								"north": {"uv": [7.5, 16], "uv_size": [1.5, 0.5]},
								"east": {"uv": [11, 14.5], "uv_size": [2.5, 0.5]},
								"south": {"uv": [9, 16], "uv_size": [1.5, 0.5]},
								"west": {"uv": [15, 11.5], "uv_size": [2.5, 0.5]},
								"up": {"uv": [19, 9], "uv_size": [1.5, 2.5]},
								"down": {"uv": [17.5, 11.5], "uv_size": [1.5, -2.5]}
							}
						},
						{
							"origin": [0.08115, -2.525, 8],
							"size": [0.15, 0.15, 0.25],
							"uv": {
								"north": {"uv": [17, 5], "uv_size": [0.5, 0.5]},
								"east": {"uv": [6, 17], "uv_size": [0.5, 0.5]},
								"south": {"uv": [17, 6], "uv_size": [0.5, 0.5]},
								"west": {"uv": [7, 17], "uv_size": [0.5, 0.5]},
								"up": {"uv": [17, 7], "uv_size": [0.5, 0.5]},
								"down": {"uv": [8, 17.5], "uv_size": [0.5, -0.5]}
							}
						},
						{
							"origin": [0.15616, -2.63107, 8.01],
							"size": [0.15, 0.225, 0.23],
							"pivot": [0.23115, -2.48107, 8.125],
							"rotation": [0, 0, -45],
							"uv": {
								"north": {"uv": [17, 8], "uv_size": [0.5, 0.5]},
								"east": {"uv": [9, 17], "uv_size": [0.5, 0.5]},
								"south": {"uv": [10, 17], "uv_size": [0.5, 0.5]},
								"west": {"uv": [11, 17], "uv_size": [0.5, 0.5]},
								"up": {"uv": [17, 11], "uv_size": [0.5, 0.5]},
								"down": {"uv": [12, 17.5], "uv_size": [0.5, -0.5]}
							}
						},
						{
							"origin": [-0.29385, -2.63107, 8.01],
							"size": [0.15, 0.225, 0.23],
							"pivot": [-0.21884, -2.48107, 8.125],
							"rotation": [0, 0, 45],
							"uv": {
								"north": {"uv": [13, 17], "uv_size": [0.5, 0.5]},
								"east": {"uv": [14, 17], "uv_size": [0.5, 0.5]},
								"south": {"uv": [17, 14], "uv_size": [0.5, 0.5]},
								"west": {"uv": [15, 17], "uv_size": [0.5, 0.5]},
								"up": {"uv": [17, 15], "uv_size": [0.5, 0.5]},
								"down": {"uv": [16, 17.5], "uv_size": [0.5, -0.5]}
							}
						},
						{
							"origin": [-0.21884, -2.525, 8],
							"size": [0.15, 0.15, 0.25],
							"uv": {
								"north": {"uv": [17, 16], "uv_size": [0.5, 0.5]},
								"east": {"uv": [17, 17], "uv_size": [0.5, 0.5]},
								"south": {"uv": [0, 18], "uv_size": [0.5, 0.5]},
								"west": {"uv": [18, 0], "uv_size": [0.5, 0.5]},
								"up": {"uv": [1, 18], "uv_size": [0.5, 0.5]},
								"down": {"uv": [18, 1.5], "uv_size": [0.5, -0.5]}
							}
						},
						{
							"origin": [-0.74385, -3.675, 7.6],
							"size": [1.5, 1.15, 1.35],
							"uv": {
								"north": {"uv": [15, 1], "uv_size": [1.5, 1]},
								"east": {"uv": [2, 15], "uv_size": [1.5, 1]},
								"south": {"uv": [15, 3], "uv_size": [1.5, 1]},
								"west": {"uv": [4, 15], "uv_size": [1.5, 1]},
								"up": {"uv": [8, 13], "uv_size": [1.5, 1.5]},
								"down": {"uv": [13, 10.5], "uv_size": [1.5, -1.5]}
							}
						},
						{
							"origin": [-0.49385, -3.675, 8.95],
							"size": [1, 0.9, 0.35],
							"uv": {
								"north": {"uv": [15, 12], "uv_size": [1, 1]},
								"east": {"uv": [5, 16], "uv_size": [0.5, 1]},
								"south": {"uv": [13, 15], "uv_size": [1, 1]},
								"west": {"uv": [16, 14], "uv_size": [0.5, 1]},
								"up": {"uv": [15, 16], "uv_size": [1, 0.5]},
								"down": {"uv": [16, 15.5], "uv_size": [1, -0.5]}
							}
						}
					]
				},
				{
					"name": "body",
					"parent": "gun_body",
					"pivot": [-0.475, -5.025, 1.5]
				},
				{
					"name": "sights",
					"parent": "body",
					"pivot": [-0.475, -0.62625, 17.5625]
				},
				{
					"name": "barrels",
					"parent": "gun_body",
					"pivot": [-0.0052, -4.9796, 3.3544],
					"rotation": [90, 0, 0]
				},
				{
					"name": "standard_barrel",
					"parent": "barrels",
					"pivot": [-0.0052, -4.97963, 3.35435],
					"rotation": [-90, 0, 0],
					"cubes": [
						{
							"origin": [0.08293, -3.825, 2.625],
							"size": [1, 1, 3],
							"uv": {
								"north": {"uv": [18.5, 7.5], "uv_size": [1.5, 1.5]},
								"east": {"uv": [18.5, 1.5], "uv_size": [4.5, 1.5]},
								"south": {"uv": [20, 7.5], "uv_size": [1.5, 1.5]},
								"west": {"uv": [18.5, 0], "uv_size": [4.5, 1.5]},
								"up": {"uv": [18.5, 3], "uv_size": [1.5, 4.5]},
								"down": {"uv": [20, 7.5], "uv_size": [1.5, -4.5]}
							}
						},
						{
							"origin": [-1.04207, -3.825, 2.625],
							"size": [1, 1, 3],
							"uv": {
								"north": {"uv": [18.5, 7.5], "uv_size": [1.5, 1.5]},
								"east": {"uv": [18.5, 1.5], "uv_size": [4.5, 1.5]},
								"south": {"uv": [20, 7.5], "uv_size": [1.5, 1.5]},
								"west": {"uv": [18.5, 0], "uv_size": [4.5, 1.5]},
								"up": {"uv": [18.5, 3], "uv_size": [1.5, 4.5]},
								"down": {"uv": [20, 7.5], "uv_size": [1.5, -4.5]}
							}
						},
						{
							"origin": [0.08293, -4.95, 2.625],
							"size": [1, 1, 3],
							"uv": {
								"north": {"uv": [18.5, 7.5], "uv_size": [1.5, 1.5]},
								"east": {"uv": [18.5, 1.5], "uv_size": [4.5, 1.5]},
								"south": {"uv": [20, 7.5], "uv_size": [1.5, 1.5]},
								"west": {"uv": [18.5, 0], "uv_size": [4.5, 1.5]},
								"up": {"uv": [18.5, 3], "uv_size": [1.5, 4.5]},
								"down": {"uv": [20, 7.5], "uv_size": [1.5, -4.5]}
							}
						},
						{
							"origin": [-1.04207, -4.95, 2.625],
							"size": [1, 1, 3],
							"uv": {
								"north": {"uv": [18.5, 7.5], "uv_size": [1.5, 1.5]},
								"east": {"uv": [18.5, 1.5], "uv_size": [4.5, 1.5]},
								"south": {"uv": [20, 7.5], "uv_size": [1.5, 1.5]},
								"west": {"uv": [18.5, 0], "uv_size": [4.5, 1.5]},
								"up": {"uv": [18.5, 3], "uv_size": [1.5, 4.5]},
								"down": {"uv": [20, 7.5], "uv_size": [1.5, -4.5]}
							}
						},
						{
							"origin": [-1.24881, -5.15282, 3.25],
							"size": [2.5, 2, 2.5],
							"uv": {
								"north": {"uv": [3, 4], "uv_size": [2.5, 2]},
								"east": {"uv": [3, 6], "uv_size": [2.5, 2]},
								"south": {"uv": [6, 3], "uv_size": [2.5, 2]},
								"west": {"uv": [6, 5], "uv_size": [2.5, 2]},
								"up": {"uv": [0, 4], "uv_size": [2.5, 2.5]},
								"down": {"uv": [4, 2.5], "uv_size": [2.5, -2.5]}
							}
						},
						{
							"origin": [-0.03134, -2.525, 4.125],
							"size": [0.075, 0.2, 0.3],
							"uv": {
								"north": {"uv": [17, 1], "uv_size": [0.5, 0.5]},
								"east": {"uv": [2, 17], "uv_size": [0.5, 0.5]},
								"south": {"uv": [3, 17], "uv_size": [0.5, 0.5]},
								"west": {"uv": [17, 3], "uv_size": [0.5, 0.5]},
								"up": {"uv": [17, 4], "uv_size": [0.5, 0.5]},
								"down": {"uv": [5, 17.5], "uv_size": [0.5, -0.5]}
							}
						},
						{
							"origin": [-0.74385, -3.1625, 4],
							"size": [1.5, 0.6376, 1.6125],
							"uv": {
								"north": {"uv": [7, 16.5], "uv_size": [1.5, 0.5]},
								"east": {"uv": [11, 15], "uv_size": [2, 0.5]},
								"south": {"uv": [8.5, 16.5], "uv_size": [1.5, 0.5]},
								"west": {"uv": [15, 11], "uv_size": [2, 0.5]},
								"up": {"uv": [11, 4], "uv_size": [1.5, 2]},
								"down": {"uv": [14.5, 9], "uv_size": [1.5, -2]}
							}
						},
						{
							"origin": [-0.73135, -2.93, 3.225],
							"size": [1.475, 0.4, 0.775],
							"pivot": [0.00615, -2.525, 3.975],
							"rotation": [22.5, 0, 0],
							"uv": {
								"north": {"uv": [16, 9], "uv_size": [1.5, 0.5]},
								"east": {"uv": [17, 0], "uv_size": [1, 0.5]},
								"south": {"uv": [16, 10.5], "uv_size": [1.5, 0.5]},
								"west": {"uv": [1, 17], "uv_size": [1, 0.5]},
								"up": {"uv": [15, 6], "uv_size": [1.5, 1]},
								"down": {"uv": [7, 16], "uv_size": [1.5, -1]}
							}
						}
					]
				},
				{
					"name": "magazine",
					"parent": "gun_body",
					"pivot": [0.025, -7.68876, 8.5787]
				},
				{
					"name": "standard_mag",
					"parent": "magazine",
					"pivot": [-0.475, -7.43876, 4.3287],
					"cubes": [
						{
							"origin": [-0.45385, -7.775, 7.4],
							"size": [0.92, 0.5, 1.8],
							"pivot": [-0.49385, -7.125, 9],
							"rotation": [22.5, 0, 0],
							"uv": {
								"north": {"uv": [16, 16], "uv_size": [1, 0.5]},
								"east": {"uv": [2, 16], "uv_size": [2, 0.5]},
								"south": {"uv": [0, 17], "uv_size": [1, 0.5]},
								"west": {"uv": [16, 2], "uv_size": [2, 0.5]},
								"up": {"uv": [14, 0], "uv_size": [1, 2]},
								"down": {"uv": [1, 16], "uv_size": [1, -2]}
							}
						}
					]
				},
				{
					"name": "magazine_2",
					"parent": "gun_body",
					"pivot": [0, -7.675, 8.5]
				},
				{
					"name": "attachment_bone",
					"parent": "gun_body",
					"pivot": [-0.47688, -6.25375, 4.74059]
				},
				{
					"name": "left_arm",
					"parent": "gun_body",
					"pivot": [5.525, -1.1182, 6.00305],
					"cubes": [
						{
							"origin": [4.275, -6.9182, 4.75305],
							"size": [2.5, 10, 2.5],
							"uv": {
								"north": {"uv": [0, 0], "uv_size": [0.5, 0.5]},
								"east": {"uv": [0, 0], "uv_size": [0.5, 0.5]},
								"south": {"uv": [0, 0], "uv_size": [0.5, 0.5]},
								"west": {"uv": [0, 0], "uv_size": [0.5, 0.5]},
								"up": {"uv": [0.5, 0.5], "uv_size": [-0.5, -0.5]},
								"down": {"uv": [0.5, 0.5], "uv_size": [-0.5, -0.5]}
							}
						}
					]
				},
				{
					"name": "right_arm",
					"parent": "gun_body",
					"pivot": [-6.475, -3.1182, 6.00305],
					"cubes": [
						{
							"origin": [-7.725, -6.9182, 4.75305],
							"size": [2.5, 10, 2.5],
							"uv": {
								"north": {"uv": [0, 0], "uv_size": [0.5, 0.5]},
								"east": {"uv": [0, 0], "uv_size": [0.5, 0.5]},
								"south": {"uv": [0, 0], "uv_size": [0.5, 0.5]},
								"west": {"uv": [0, 0], "uv_size": [0.5, 0.5]},
								"up": {"uv": [0.5, 0.5], "uv_size": [-0.5, -0.5]},
								"down": {"uv": [0.5, 0.5], "uv_size": [-0.5, -0.5]}
							}
						}
					]
				},
				{
					"name": "left_wing",
					"parent": "gun_body",
					"pivot": [0.72686, -4.40233, 6.08285],
					"cubes": [
						{
							"origin": [0.75, -4.40233, 5.65233],
							"size": [1.75, 2.75, 0],
							"pivot": [0.5, -4.27733, 5.65233],
							"rotation": [0, -22.5, 0],
							"uv": {
								"south": {"uv": [0, 18.5], "uv_size": [2, 3]}
							}
						}
					]
				},
				{
					"name": "right_wing",
					"parent": "gun_body",
					"pivot": [-0.72686, -4.40233, 6.08285],
					"cubes": [
						{
							"origin": [-2.5, -4.40233, 5.65233],
							"size": [1.75, 2.75, 0],
							"pivot": [-0.5, -4.27733, 5.65233],
							"rotation": [0, 22.5, 0],
							"uv": {
								"south": {"uv": [2, 18.5], "uv_size": [2, 3]}
							}
						}
					]
				},
				{
					"name": "idklol",
					"parent": "gun_body",
					"pivot": [0.00615, -3.225, 9.45],
					"cubes": [
						{
							"origin": [0.00615, -3.35, 9.2],
							"size": [0, 0.95, 0.95],
							"pivot": [0.00615, -3.225, 9.45],
							"rotation": [22.5, 0, 0],
							"uv": {
								"west": {"uv": [15, 15], "uv_size": [1, 1]}
							}
						}
					]
				}
			]
		}
	]
}