{
	"format_version": "1.12.0",
	"minecraft:geometry": [
		{
			"description": {
				"identifier": "geometry.unknown",
				"texture_width": 32,
				"texture_height": 32,
				"visible_bounds_width": 4,
				"visible_bounds_height": 4,
				"visible_bounds_offset": [0, 0, 0]
			},
			"bones": [
				{
					"name": "gun_body2",
					"pivot": [-0.475, -5.025, 0]
				},
				{
					"name": "gun_body",
					"parent": "gun_body2",
					"pivot": [-0.475, -3.525, 7],
					"cubes": [
						{
							"origin": [-0.5439, -7.525, 6.05],
							"size": [1.1, 4, 1.95],
							"pivot": [-0.58385, -6.625, 7.5],
							"rotation": [22.5, 0, 0],
							"uv": {
								"north": {"uv": [13, 2], "uv_size": [1, 4]},
								"east": {"uv": [10, 8], "uv_size": [2, 4]},
								"south": {"uv": [17, 9], "uv_size": [1, 4]},
								"west": {"uv": [2, 11], "uv_size": [2, 4]},
								"up": {"uv": [11, 6], "uv_size": [1, 2]},
								"down": {"uv": [16, 11], "uv_size": [1, -2]}
							}
						},
						{
							"origin": [-0.00385, -5.875, 3.6],
							"size": [0, 1.45, 2],
							"uv": {
								"north": {"uv": [0, 0], "uv_size": [0, 1.5]},
								"east": {"uv": [14, 17], "uv_size": [2, 1.5]},
								"south": {"uv": [0, 0], "uv_size": [0, 1.5]},
								"west": {"uv": [16, 17], "uv_size": [2, 1.5]},
								"up": {"uv": [0, 0], "uv_size": [0, 2]},
								"down": {"uv": [0, 2], "uv_size": [0, -2]}
							}
						},
						{
							"origin": [-0.66885, -2.525, -1.9],
							"size": [1.35, 0.25, 5],
							"uv": {
								"north": {"uv": [3, 22], "uv_size": [1.5, 0.5]},
								"east": {"uv": [18, 6], "uv_size": [5, 0.5]},
								"south": {"uv": [22, 3], "uv_size": [1.5, 0.5]},
								"west": {"uv": [18, 7], "uv_size": [5, 0.5]},
								"up": {"uv": [4, 11], "uv_size": [1.5, 5]},
								"down": {"uv": [0, 17], "uv_size": [1.5, -5]}
							}
						},
						{
							"origin": [-0.99385, -5.025, -1.9],
							"size": [2, 2.5, 5],
							"uv": {
								"north": {"uv": [16, 6], "uv_size": [2, 2.5]},
								"east": {"uv": [0, 0], "uv_size": [5, 2.5]},
								"south": {"uv": [0, 17], "uv_size": [2, 2.5]},
								"west": {"uv": [0, 3], "uv_size": [5, 2.5]},
								"up": {"uv": [2, 6], "uv_size": [2, 5]},
								"down": {"uv": [4, 11], "uv_size": [2, -5]}
							}
						},
						{
							"origin": [-0.99385, -5.025, 3.1],
							"size": [2, 0.5, 0.5],
							"uv": {
								"north": {"uv": [21, 17], "uv_size": [2, 0.5]},
								"east": {"uv": [25, 0], "uv_size": [0.5, 0.5]},
								"south": {"uv": [18, 21], "uv_size": [2, 0.5]},
								"west": {"uv": [1, 25], "uv_size": [0.5, 0.5]},
								"up": {"uv": [21, 18], "uv_size": [2, 0.5]},
								"down": {"uv": [20, 21.5], "uv_size": [2, -0.5]}
							}
						},
						{
							"origin": [-0.03134, -2.275, -1.5],
							"size": [0.075, 0.2, 0.3],
							"uv": {
								"north": {"uv": [10, 24], "uv_size": [0.5, 0.5]},
								"east": {"uv": [24, 10], "uv_size": [0.5, 0.5]},
								"south": {"uv": [11, 24], "uv_size": [0.5, 0.5]},
								"west": {"uv": [24, 11], "uv_size": [0.5, 0.5]},
								"up": {"uv": [12, 24], "uv_size": [0.5, 0.5]},
								"down": {"uv": [24, 12.5], "uv_size": [0.5, -0.5]}
							}
						},
						{
							"origin": [-0.74385, -4.525, 3.1],
							"size": [1.5, 2, 4.35],
							"uv": {
								"north": {"uv": [2, 18], "uv_size": [1.5, 2]},
								"east": {"uv": [6, 6], "uv_size": [4.5, 2]},
								"south": {"uv": [18, 2], "uv_size": [1.5, 2]},
								"west": {"uv": [7, 0], "uv_size": [4.5, 2]},
								"up": {"uv": [12, 6], "uv_size": [1.5, 4.5]},
								"down": {"uv": [10, 16.5], "uv_size": [1.5, -4.5]}
							}
						},
						{
							"origin": [-0.66885, -2.525, 3.1],
							"size": [1.35, 0.25, 4],
							"uv": {
								"north": {"uv": [22, 5], "uv_size": [1.5, 0.5]},
								"east": {"uv": [18, 12], "uv_size": [4, 0.5]},
								"south": {"uv": [7, 22], "uv_size": [1.5, 0.5]},
								"west": {"uv": [20, 13], "uv_size": [4, 0.5]},
								"up": {"uv": [6, 14], "uv_size": [1.5, 4]},
								"down": {"uv": [14, 11], "uv_size": [1.5, -4]}
							}
						},
						{
							"origin": [-0.41885, -3.7, 7.45],
							"size": [0.85, 0.85, 0.25],
							"pivot": [0.00615, -3.275, 7.5625],
							"rotation": [0, 0, 45],
							"uv": {
								"north": {"uv": [2, 22], "uv_size": [1, 1]},
								"east": {"uv": [24, 6], "uv_size": [0.5, 1]},
								"south": {"uv": [22, 2], "uv_size": [1, 1]},
								"west": {"uv": [24, 7], "uv_size": [0.5, 1]},
								"up": {"uv": [8, 24], "uv_size": [1, 0.5]},
								"down": {"uv": [9, 24.5], "uv_size": [1, -0.5]}
							}
						}
					]
				},
				{
					"name": "sights",
					"parent": "gun_body",
					"pivot": [0, 0, 0.25],
					"cubes": [
						{
							"origin": [0.08115, -2.275, 6.75],
							"size": [0.15, 0.15, 0.25],
							"uv": {
								"north": {"uv": [13, 24], "uv_size": [0.5, 0.5]},
								"east": {"uv": [24, 13], "uv_size": [0.5, 0.5]},
								"south": {"uv": [14, 24], "uv_size": [0.5, 0.5]},
								"west": {"uv": [24, 14], "uv_size": [0.5, 0.5]},
								"up": {"uv": [15, 24], "uv_size": [0.5, 0.5]},
								"down": {"uv": [24, 15.5], "uv_size": [0.5, -0.5]}
							}
						},
						{
							"origin": [-0.21884, -2.275, 6.75],
							"size": [0.15, 0.15, 0.25],
							"uv": {
								"north": {"uv": [22, 24], "uv_size": [0.5, 0.5]},
								"east": {"uv": [24, 22], "uv_size": [0.5, 0.5]},
								"south": {"uv": [23, 24], "uv_size": [0.5, 0.5]},
								"west": {"uv": [24, 23], "uv_size": [0.5, 0.5]},
								"up": {"uv": [24, 24], "uv_size": [0.5, 0.5]},
								"down": {"uv": [0, 25.5], "uv_size": [0.5, -0.5]}
							}
						},
						{
							"origin": [-0.29385, -2.38107, 6.76],
							"size": [0.15, 0.225, 0.23],
							"pivot": [-0.21884, -2.23107, 6.875],
							"rotation": [0, 0, 45],
							"uv": {
								"north": {"uv": [19, 24], "uv_size": [0.5, 0.5]},
								"east": {"uv": [24, 19], "uv_size": [0.5, 0.5]},
								"south": {"uv": [20, 24], "uv_size": [0.5, 0.5]},
								"west": {"uv": [24, 20], "uv_size": [0.5, 0.5]},
								"up": {"uv": [21, 24], "uv_size": [0.5, 0.5]},
								"down": {"uv": [24, 21.5], "uv_size": [0.5, -0.5]}
							}
						},
						{
							"origin": [0.15616, -2.38107, 6.76],
							"size": [0.15, 0.225, 0.23],
							"pivot": [0.23115, -2.23107, 6.875],
							"rotation": [0, 0, -45],
							"uv": {
								"north": {"uv": [16, 24], "uv_size": [0.5, 0.5]},
								"east": {"uv": [24, 16], "uv_size": [0.5, 0.5]},
								"south": {"uv": [17, 24], "uv_size": [0.5, 0.5]},
								"west": {"uv": [24, 17], "uv_size": [0.5, 0.5]},
								"up": {"uv": [18, 24], "uv_size": [0.5, 0.5]},
								"down": {"uv": [24, 18.5], "uv_size": [0.5, -0.5]}
							}
						}
					]
				},
				{
					"name": "body",
					"parent": "gun_body",
					"pivot": [-0.475, -5.025, 0]
				},
				{
					"name": "bolt",
					"parent": "body",
					"pivot": [-1.60146, -3.32684, 3.26042],
					"cubes": [
						{
							"origin": [-1.54385, -3.525, 3.425],
							"size": [0.5, 0.5, 0.5],
							"pivot": [-1.29385, -3.275, 3.675],
							"rotation": [-45, 0, 0],
							"uv": {
								"north": {"uv": [25, 1], "uv_size": [0.5, 0.5]},
								"east": {"uv": [2, 25], "uv_size": [0.5, 0.5]},
								"south": {"uv": [25, 2], "uv_size": [0.5, 0.5]},
								"west": {"uv": [3, 25], "uv_size": [0.5, 0.5]},
								"up": {"uv": [25, 3], "uv_size": [0.5, 0.5]},
								"down": {"uv": [4, 25.5], "uv_size": [0.5, -0.5]}
							}
						},
						{
							"origin": [-1.04385, -3.475, 3.475],
							"size": [0.3, 0.4, 0.4],
							"pivot": [-0.89385, -3.275, 3.675],
							"rotation": [-45, 0, 0],
							"uv": {
								"north": {"uv": [25, 4], "uv_size": [0.5, 0.5]},
								"east": {"uv": [5, 25], "uv_size": [0.5, 0.5]},
								"south": {"uv": [25, 5], "uv_size": [0.5, 0.5]},
								"west": {"uv": [6, 25], "uv_size": [0.5, 0.5]},
								"up": {"uv": [25, 6], "uv_size": [0.5, 0.5]},
								"down": {"uv": [7, 25.5], "uv_size": [0.5, -0.5]}
							}
						},
						{
							"origin": [0.75615, -3.475, 3.475],
							"size": [0.3, 0.4, 0.4],
							"pivot": [0.90615, -3.275, 3.675],
							"rotation": [-45, 0, 0],
							"uv": {
								"north": {"uv": [25, 4], "uv_size": [0.5, 0.5]},
								"east": {"uv": [5, 25], "uv_size": [0.5, 0.5]},
								"south": {"uv": [25, 5], "uv_size": [0.5, 0.5]},
								"west": {"uv": [6, 25], "uv_size": [0.5, 0.5]},
								"up": {"uv": [25, 6], "uv_size": [0.5, 0.5]},
								"down": {"uv": [7, 25.5], "uv_size": [0.5, -0.5]}
							}
						},
						{
							"origin": [1.05615, -3.525, 3.425],
							"size": [0.5, 0.5, 0.5],
							"pivot": [1.30615, -3.275, 3.675],
							"rotation": [-45, 0, 0],
							"uv": {
								"north": {"uv": [25, 1], "uv_size": [0.5, 0.5]},
								"east": {"uv": [2, 25], "uv_size": [0.5, 0.5]},
								"south": {"uv": [25, 2], "uv_size": [0.5, 0.5]},
								"west": {"uv": [3, 25], "uv_size": [0.5, 0.5]},
								"up": {"uv": [25, 3], "uv_size": [0.5, 0.5]},
								"down": {"uv": [4, 25.5], "uv_size": [0.5, -0.5]}
							}
						}
					]
				},
				{
					"name": "barrels",
					"parent": "gun_body",
					"pivot": [-0.475, -5.025, 0]
				},
				{
					"name": "standard_barrel",
					"parent": "barrels",
					"pivot": [-0.26287, -2.72733, -9.14767],
					"cubes": [
						{
							"origin": [-0.66884, -3.96036, -2.4],
							"size": [1.35, 1.35, 0.5],
							"pivot": [0.00616, -3.28536, -2.15],
							"rotation": [0, 0, 45],
							"uv": {
								"north": {"uv": [18, 8], "uv_size": [1.5, 1.5]},
								"east": {"uv": [22, 8], "uv_size": [0.5, 1.5]},
								"south": {"uv": [18, 10], "uv_size": [1.5, 1.5]},
								"west": {"uv": [9, 22], "uv_size": [0.5, 1.5]},
								"up": {"uv": [10, 22], "uv_size": [1.5, 0.5]},
								"down": {"uv": [22, 10.5], "uv_size": [1.5, -0.5]}
							}
						},
						{
							"origin": [-0.41707, -3.9, -1.4],
							"size": [1, 1, 0.5],
							"pivot": [0.18293, -3.25, -2.275],
							"rotation": [0, 0, 45],
							"uv": {
								"north": {"uv": [10, 21], "uv_size": [1, 1]},
								"east": {"uv": [8, 23], "uv_size": [0.5, 1]},
								"south": {"uv": [11, 21], "uv_size": [1, 1]},
								"west": {"uv": [10, 23], "uv_size": [0.5, 1]},
								"up": {"uv": [11, 23], "uv_size": [1, 0.5]},
								"down": {"uv": [23, 11.5], "uv_size": [1, -0.5]}
							}
						}
					]
				},
				{
					"name": "extended_barrel",
					"parent": "barrels",
					"pivot": [-0.26287, -2.72733, -9.14767],
					"cubes": [
						{
							"origin": [-0.41707, -3.9, -4.9],
							"size": [1, 1, 4],
							"pivot": [0.18293, -3.25, -2.275],
							"rotation": [0, 0, 45],
							"uv": {
								"north": {"uv": [14, 21], "uv_size": [1, 1]},
								"east": {"uv": [17, 0], "uv_size": [4, 1]},
								"south": {"uv": [15, 21], "uv_size": [1, 1]},
								"west": {"uv": [17, 1], "uv_size": [4, 1]},
								"up": {"uv": [10, 17], "uv_size": [1, 4]},
								"down": {"uv": [11, 21], "uv_size": [1, -4]}
							}
						},
						{
							"origin": [-0.64384, -3.95, -2.9],
							"size": [1.35, 1.35, 1],
							"pivot": [0.00615, -3.25, -2.775],
							"rotation": [0, 0, 45],
							"uv": {
								"north": {"uv": [20, 10], "uv_size": [1.5, 1.5]},
								"east": {"uv": [20, 15], "uv_size": [1, 1.5]},
								"south": {"uv": [12, 20], "uv_size": [1.5, 1.5]},
								"west": {"uv": [20, 17], "uv_size": [1, 1.5]},
								"up": {"uv": [20, 19], "uv_size": [1.5, 1]},
								"down": {"uv": [20, 21], "uv_size": [1.5, -1]}
							}
						},
						{
							"origin": [-0.66884, -3.96036, -5.4],
							"size": [1.35, 1.35, 0.5],
							"pivot": [0.00616, -3.28536, -5.15],
							"rotation": [0, 0, 45],
							"uv": {
								"north": {"uv": [18, 8], "uv_size": [1.5, 1.5]},
								"east": {"uv": [22, 8], "uv_size": [0.5, 1.5]},
								"south": {"uv": [18, 10], "uv_size": [1.5, 1.5]},
								"west": {"uv": [9, 22], "uv_size": [0.5, 1.5]},
								"up": {"uv": [10, 22], "uv_size": [1.5, 0.5]},
								"down": {"uv": [22, 10.5], "uv_size": [1.5, -0.5]}
							}
						}
					]
				},
				{
					"name": "muzzle_brake",
					"parent": "barrels",
					"pivot": [-0.68996, -4.15, -3.175],
					"cubes": [
						{
							"origin": [-0.52105, -3.71674, -4.69056],
							"size": [0.9555, 0.9555, 0.39244],
							"pivot": [-0.0433, -3.29017, -4.51497],
							"rotation": [0, 0, 45],
							"uv": {
								"north": {"uv": [21, 15], "uv_size": [1, 1]},
								"east": {"uv": [23, 12], "uv_size": [0.5, 1]},
								"south": {"uv": [16, 21], "uv_size": [1, 1]},
								"west": {"uv": [13, 23], "uv_size": [0.5, 1]},
								"up": {"uv": [14, 23], "uv_size": [1, 0.5]},
								"down": {"uv": [23, 15.5], "uv_size": [1, -0.5]}
							}
						},
						{
							"origin": [-0.69167, -3.88736, -2.78313],
							"size": [1.29675, 1.29675, 0.39244],
							"pivot": [-0.0433, -3.29017, -4.12254],
							"rotation": [0, 0, 45],
							"uv": {
								"north": {"uv": [18, 17], "uv_size": [1.5, 1.5]},
								"east": {"uv": [15, 22], "uv_size": [0.5, 1.5]},
								"south": {"uv": [14, 19], "uv_size": [1.5, 1.5]},
								"west": {"uv": [22, 15], "uv_size": [0.5, 1.5]},
								"up": {"uv": [16, 22], "uv_size": [1.5, 0.5]},
								"down": {"uv": [18, 22.5], "uv_size": [1.5, -0.5]}
							}
						},
						{
							"origin": [-0.69167, -3.88736, -3.90569],
							"size": [0.435, 0, 1.12256],
							"pivot": [-0.0433, -3.29017, -4.51497],
							"rotation": [0, 0, 45],
							"uv": {
								"north": {"uv": [0, 0], "uv_size": [0.5, 0]},
								"east": {"uv": [0, 0], "uv_size": [1, 0]},
								"south": {"uv": [0, 0], "uv_size": [0.5, 0]},
								"west": {"uv": [0, 0], "uv_size": [1, 0]},
								"up": {"uv": [16, 23], "uv_size": [0.5, 1]},
								"down": {"uv": [23, 17], "uv_size": [0.5, -1]}
							}
						},
						{
							"origin": [-0.69167, -3.88736, -3.90569],
							"size": [0, 0.435, 1.12256],
							"pivot": [-0.0433, -3.29017, -4.51497],
							"rotation": [0, 0, 45],
							"uv": {
								"north": {"uv": [0, 0], "uv_size": [0, 0.5]},
								"east": {"uv": [17, 23], "uv_size": [1, 0.5]},
								"south": {"uv": [0, 0], "uv_size": [0, 0.5]},
								"west": {"uv": [23, 17], "uv_size": [1, 0.5]},
								"up": {"uv": [0, 0], "uv_size": [0, 1]},
								"down": {"uv": [0, 1], "uv_size": [0, -1]}
							}
						},
						{
							"origin": [0.24246, -3.88736, -3.90569],
							"size": [0.435, 0, 1.12256],
							"pivot": [0.02909, -3.29017, -4.51497],
							"rotation": [0, 0, -45],
							"uv": {
								"north": {"uv": [0, 0], "uv_size": [0.5, 0]},
								"east": {"uv": [0, 0], "uv_size": [1, 0]},
								"south": {"uv": [0, 0], "uv_size": [0.5, 0]},
								"west": {"uv": [0, 0], "uv_size": [1, 0]},
								"up": {"uv": [18, 23], "uv_size": [0.5, 1]},
								"down": {"uv": [23, 19], "uv_size": [0.5, -1]}
							}
						},
						{
							"origin": [0.67746, -3.88736, -3.90569],
							"size": [0, 0.435, 1.12256],
							"pivot": [0.02909, -3.29017, -4.51497],
							"rotation": [0, 0, -45],
							"uv": {
								"north": {"uv": [0, 0], "uv_size": [0, 0.5]},
								"east": {"uv": [19, 23], "uv_size": [1, 0.5]},
								"south": {"uv": [0, 0], "uv_size": [0, 0.5]},
								"west": {"uv": [23, 19], "uv_size": [1, 0.5]},
								"up": {"uv": [0, 1], "uv_size": [0, -1]},
								"down": {"uv": [0, 1], "uv_size": [0, -1]}
							}
						},
						{
							"origin": [-0.65548, -3.90235, -3.90569],
							"size": [0, 0.435, 1.12256],
							"pivot": [-0.00711, -3.25398, -3.26941],
							"rotation": [0, 0, -45],
							"uv": {
								"north": {"uv": [0, 0], "uv_size": [0, 0.5]},
								"east": {"uv": [23, 20], "uv_size": [1, 0.5]},
								"south": {"uv": [0, 0], "uv_size": [0, 0.5]},
								"west": {"uv": [21, 23], "uv_size": [1, 0.5]},
								"up": {"uv": [0, 1], "uv_size": [0, -1]},
								"down": {"uv": [0, 1], "uv_size": [0, -1]}
							}
						},
						{
							"origin": [-0.65548, -3.90235, -3.90569],
							"size": [0.435, 0, 1.12256],
							"pivot": [-0.00711, -3.25398, -3.26941],
							"rotation": [0, 0, -45],
							"uv": {
								"north": {"uv": [0, 0], "uv_size": [0.5, 0]},
								"east": {"uv": [0, 0], "uv_size": [1, 0]},
								"south": {"uv": [0, 0], "uv_size": [0.5, 0]},
								"west": {"uv": [0, 0], "uv_size": [1, 0]},
								"up": {"uv": [22, 23], "uv_size": [0.5, 1]},
								"down": {"uv": [23, 23], "uv_size": [0.5, -1]}
							}
						},
						{
							"origin": [0.20627, -2.6056, -3.90569],
							"size": [0.435, 0, 1.12256],
							"pivot": [-0.00711, -3.25398, -3.26941],
							"rotation": [0, 0, -45],
							"uv": {
								"north": {"uv": [0, 0], "uv_size": [0.5, 0]},
								"east": {"uv": [0, 0], "uv_size": [1, 0]},
								"south": {"uv": [0, 0], "uv_size": [0.5, 0]},
								"west": {"uv": [0, 0], "uv_size": [1, 0]},
								"up": {"uv": [23, 23], "uv_size": [0.5, 1]},
								"down": {"uv": [24, 1], "uv_size": [0.5, -1]}
							}
						},
						{
							"origin": [0.64127, -3.0406, -3.90569],
							"size": [0, 0.435, 1.12256],
							"pivot": [-0.00711, -3.25398, -3.26941],
							"rotation": [0, 0, -45],
							"uv": {
								"north": {"uv": [0, 0], "uv_size": [0, 0.5]},
								"east": {"uv": [24, 1], "uv_size": [1, 0.5]},
								"south": {"uv": [0, 0], "uv_size": [0, 0.5]},
								"west": {"uv": [24, 3], "uv_size": [1, 0.5]},
								"up": {"uv": [0, 1], "uv_size": [0, -1]},
								"down": {"uv": [0, 1], "uv_size": [0, -1]}
							}
						},
						{
							"origin": [-0.69167, -3.88736, -4.29812],
							"size": [1.29675, 1.29675, 0.39243],
							"pivot": [-0.0433, -3.29017, -4.12254],
							"rotation": [0, 0, 45],
							"uv": {
								"north": {"uv": [16, 19], "uv_size": [1.5, 1.5]},
								"east": {"uv": [22, 19], "uv_size": [0.5, 1.5]},
								"south": {"uv": [18, 19], "uv_size": [1.5, 1.5]},
								"west": {"uv": [20, 22], "uv_size": [0.5, 1.5]},
								"up": {"uv": [21, 22], "uv_size": [1.5, 0.5]},
								"down": {"uv": [22, 21.5], "uv_size": [1.5, -0.5]}
							}
						}
					]
				},
				{
					"name": "advanced_silencer",
					"parent": "barrels",
					"pivot": [-0.29002, -4.15, 3.6125],
					"cubes": [
						{
							"origin": [-0.84688, -4.025, -7.475],
							"size": [1.5, 1.5, 4.575],
							"pivot": [-0.04687, -3.4, -5.9625],
							"rotation": [0, 0, 45],
							"uv": {
								"north": {"uv": [0, 20], "uv_size": [1.5, 1.5]},
								"east": {"uv": [12, 0], "uv_size": [4.5, 1.5]},
								"south": {"uv": [2, 20], "uv_size": [1.5, 1.5]},
								"west": {"uv": [12, 11], "uv_size": [4.5, 1.5]},
								"up": {"uv": [12, 13], "uv_size": [1.5, 4.5]},
								"down": {"uv": [14, 6.5], "uv_size": [1.5, -4.5]}
							}
						},
						{
							"origin": [-0.67366, -3.675, -2.9],
							"size": [1.15, 1.15, 0.5],
							"pivot": [-0.22366, -3.3, -5.4625],
							"rotation": [0, 0, 45],
							"uv": {
								"north": {"uv": [21, 16], "uv_size": [1, 1]},
								"east": {"uv": [24, 4], "uv_size": [0.5, 1]},
								"south": {"uv": [17, 21], "uv_size": [1, 1]},
								"west": {"uv": [5, 24], "uv_size": [0.5, 1]},
								"up": {"uv": [24, 5], "uv_size": [1, 0.5]},
								"down": {"uv": [6, 24.5], "uv_size": [1, -0.5]}
							}
						}
					]
				},
				{
					"name": "silencer",
					"parent": "barrels",
					"pivot": [-0.48497, 3.005, -3.8875],
					"cubes": [
						{
							"origin": [-0.75938, -4, -6.07187],
							"size": [1.425, 1.425, 3.68124],
							"pivot": [-0.04687, -3.34375, -4.29375],
							"rotation": [0, 0, 45],
							"uv": {
								"north": {"uv": [20, 2], "uv_size": [1.5, 1.5]},
								"east": {"uv": [14, 15], "uv_size": [3.5, 1.5]},
								"south": {"uv": [4, 20], "uv_size": [1.5, 1.5]},
								"west": {"uv": [2, 16], "uv_size": [3.5, 1.5]},
								"up": {"uv": [8, 14], "uv_size": [1.5, 3.5]},
								"down": {"uv": [16, 5.5], "uv_size": [1.5, -3.5]}
							}
						},
						{
							"origin": [1.00312, -4.98125, -4.08438],
							"size": [0, 1.675, 0.55],
							"uv": {
								"north": {"uv": [0, 0], "uv_size": [0, 1.5]},
								"east": {"uv": [0, 23], "uv_size": [0.5, 1.5]},
								"south": {"uv": [0, 0], "uv_size": [0, 1.5]},
								"west": {"uv": [23, 0], "uv_size": [0.5, 1.5]},
								"up": {"uv": [0, 0.5], "uv_size": [0, -0.5]},
								"down": {"uv": [0, 0.5], "uv_size": [0, -0.5]}
							}
						},
						{
							"origin": [-1.00313, -4.60625, -4.47812],
							"size": [0, 1.3, 0.55],
							"uv": {
								"north": {"uv": [0, 0], "uv_size": [0, 1.5]},
								"east": {"uv": [1, 23], "uv_size": [0.5, 1.5]},
								"south": {"uv": [0, 0], "uv_size": [0, 1.5]},
								"west": {"uv": [2, 23], "uv_size": [0.5, 1.5]},
								"up": {"uv": [0, 0.5], "uv_size": [0, -0.5]},
								"down": {"uv": [0, 0.5], "uv_size": [0, -0.5]}
							}
						},
						{
							"origin": [-0.54207, -4.025, -6.3125],
							"size": [1.25, 1.25, 0.5],
							"pivot": [0.18293, -3.25, -7.1875],
							"rotation": [0, 0, 45],
							"uv": {
								"north": {"uv": [20, 4], "uv_size": [1.5, 1.5]},
								"east": {"uv": [3, 23], "uv_size": [0.5, 1.5]},
								"south": {"uv": [6, 20], "uv_size": [1.5, 1.5]},
								"west": {"uv": [4, 23], "uv_size": [0.5, 1.5]},
								"up": {"uv": [23, 2], "uv_size": [1.5, 0.5]},
								"down": {"uv": [5, 23.5], "uv_size": [1.5, -0.5]}
							}
						},
						{
							"origin": [-0.71884, -4.025, -6.8125],
							"size": [1.5, 1.5, 0.5],
							"pivot": [0.00615, -3.25, -7.1875],
							"rotation": [0, 0, 45],
							"uv": {
								"north": {"uv": [8, 20], "uv_size": [1.5, 1.5]},
								"east": {"uv": [23, 6], "uv_size": [0.5, 1.5]},
								"south": {"uv": [20, 8], "uv_size": [1.5, 1.5]},
								"west": {"uv": [7, 23], "uv_size": [0.5, 1.5]},
								"up": {"uv": [23, 8], "uv_size": [1.5, 0.5]},
								"down": {"uv": [23, 9.5], "uv_size": [1.5, -0.5]}
							}
						}
					]
				},
				{
					"name": "magazine",
					"parent": "gun_body",
					"pivot": [0.025, -7.68876, 7.0787],
					"cubes": [
						{
							"origin": [-0.74385, -6.025, -1.85],
							"size": [1.5, 1.5, 5.4],
							"uv": {
								"north": {"uv": [6, 18], "uv_size": [1.5, 1.5]},
								"east": {"uv": [7, 2], "uv_size": [5.5, 1.5]},
								"south": {"uv": [8, 18], "uv_size": [1.5, 1.5]},
								"west": {"uv": [7, 4], "uv_size": [5.5, 1.5]},
								"up": {"uv": [6, 8], "uv_size": [1.5, 5.5]},
								"down": {"uv": [8, 13.5], "uv_size": [1.5, -5.5]}
							}
						}
					]
				},
				{
					"name": "left_arm",
					"parent": "magazine",
					"pivot": [5.525, -1.6182, 6.00305],
					"cubes": [
						{
							"origin": [4.275, -7.4182, 4.75305],
							"size": [2.5, 10, 2.5],
							"uv": {
								"north": {"uv": [0, 0], "uv_size": [0.5, 0.5]},
								"east": {"uv": [0, 0], "uv_size": [0.5, 0.5]},
								"south": {"uv": [0, 0], "uv_size": [0.5, 0.5]},
								"west": {"uv": [0, 0], "uv_size": [0.5, 0.5]},
								"up": {"uv": [0.5, 0.5], "uv_size": [-0.5, -0.5]},
								"down": {"uv": [0.5, 0.5], "uv_size": [-0.5, -0.5]}
							}
						}
					]
				},
				{
					"name": "magazine_2",
					"parent": "gun_body",
					"pivot": [0, -7.675, 7]
				},
				{
					"name": "attachment_bone",
					"parent": "gun_body",
					"pivot": [-0.47688, -6.25375, 3.24059]
				},
				{
					"name": "right_arm",
					"parent": "gun_body",
					"pivot": [-6.475, -3.6182, 6.00305],
					"cubes": [
						{
							"origin": [-7.725, -7.4182, 4.75305],
							"size": [2.5, 10, 2.5],
							"uv": {
								"north": {"uv": [0, 0], "uv_size": [0.5, 0.5]},
								"east": {"uv": [0, 0], "uv_size": [0.5, 0.5]},
								"south": {"uv": [0, 0], "uv_size": [0.5, 0.5]},
								"west": {"uv": [0, 0], "uv_size": [0.5, 0.5]},
								"up": {"uv": [0.5, 0.5], "uv_size": [-0.5, -0.5]},
								"down": {"uv": [0.5, 0.5], "uv_size": [-0.5, -0.5]}
							}
						}
					]
				}
			]
		}
	]
}